{
  "name": "Comoros",
  "altSpellings": [
    "KM",
    "Union of the Comoros",
    "Union des Comores",
    "Udzima wa Komori",
    "al-Itti\u1e25\u0101d al-Qumur\u012b",
    "COM"
  ],
  "area": 1862,
  "borders": [],
  "callingCodes": [
    "269"
  ],
  "capital": "Moroni",
  "capital_latlng": [
    -11.693126,
    43.254304
  ],
  "currencies": [
    "KMF"
  ],
  "demonym": "Comoran",
  "flag": "",
  "geoJSON": {},
  "ISO": {
    "alpha2": "KM",
    "alpha3": "COM"
  },
  "languages": [
    "ar",
    "fr"
  ],
  "latlng": [
    -12.16666666,
    44.25
  ],
  "nativeName": "Comores Komori \u062c\u0632\u0631 \u0627\u0644\u0642\u0645\u0631",
  "population": 763952,
  "provinces": [
    "Anjouan (Nzwani)",
    "Domoni",
    "Fomboni",
    "Grande Comore (Njazidja)",
    "Moheli (Mwali)",
    "Moroni",
    "Moutsamoudou"
  ],
  "region": "Africa",
  "subregion": "Sub-Saharan Africa",
  "timezones": [
    "UTC+03:00"
  ],
  "tld": [
    ".km"
  ],
  "translations": {
    "de": "Union der Komoren",
    "es": "Comoras",
    "fr": "Comores",
    "ja": "\u30b3\u30e2\u30ed",
    "it": "Comore"
  },
  "wiki": "http://en.wikipedia.org/wiki/comoros",
  "intermediateregion": "Eastern Africa"
}
